odoo9_addon_disable_odoo_online-9.0.1.0.0.99.dev11-py2.7-nspkg.pth
odoo9_addon_disable_odoo_online-9.0.1.0.0.99.dev11.dist-info/DESCRIPTION.rst
odoo9_addon_disable_odoo_online-9.0.1.0.0.99.dev11.dist-info/METADATA
odoo9_addon_disable_odoo_online-9.0.1.0.0.99.dev11.dist-info/RECORD
odoo9_addon_disable_odoo_online-9.0.1.0.0.99.dev11.dist-info/WHEEL
odoo9_addon_disable_odoo_online-9.0.1.0.0.99.dev11.dist-info/metadata.json
odoo9_addon_disable_odoo_online-9.0.1.0.0.99.dev11.dist-info/namespace_packages.txt
odoo9_addon_disable_odoo_online-9.0.1.0.0.99.dev11.dist-info/top_level.txt
odoo_addons/disable_odoo_online/__init__.py
odoo_addons/disable_odoo_online/__openerp__.py
odoo_addons/disable_odoo_online/data/ir_cron.xml
odoo_addons/disable_odoo_online/i18n/ca.po
odoo_addons/disable_odoo_online/i18n/de.po
odoo_addons/disable_odoo_online/i18n/disable_odoo_online.pot
odoo_addons/disable_odoo_online/i18n/es.po
odoo_addons/disable_odoo_online/i18n/fr.po
odoo_addons/disable_odoo_online/i18n/hr.po
odoo_addons/disable_odoo_online/i18n/hr_HR.po
odoo_addons/disable_odoo_online/i18n/pt_BR.po
odoo_addons/disable_odoo_online/i18n/sl.po
odoo_addons/disable_odoo_online/i18n/tr.po
odoo_addons/disable_odoo_online/model/__init__.py
odoo_addons/disable_odoo_online/model/publisher_warranty_contract.py
odoo_addons/disable_odoo_online/static/description/icon.png
odoo_addons/disable_odoo_online/static/src/js/disable_odoo_online.js
odoo_addons/disable_odoo_online/static/src/xml/base.xml
odoo_addons/disable_odoo_online/views/disable_odoo_online.xml
odoo_addons/disable_odoo_online/views/ir_ui_menu.xml
